[
    {
        "Command": "7E0",
        "Model": "Cayenne NAR",
        "Semantics": "Engine"
    },
    {
        "Command": "7E8",
        "Model": "Cayenne NAR",
        "Semantics": "Engine"
    },
    {
        "Command": "7E1",
        "Model": "Cayenne NAR",
        "Semantics": "Auto Transmission"
    },
    {
        "Command": "7E9",
        "Model": "Cayenne NAR",
        "Semantics": "Auto Transmission"
    },
    {
        "Command": "713",
        "Model": "Cayenne NAR",
        "Semantics": "ABS Brakes"
    },
    {
        "Command": "77D",
        "Model": "Cayenne NAR",
        "Semantics": "ABS Brakes"
    },
    {
        "Command": "746",
        "Model": "Cayenne NAR",
        "Semantics": "Auto HVAC"
    },
    {
        "Command": "7B0",
        "Model": "Cayenne NAR",
        "Semantics": "Auto HVAC"
    },
    {
        "Command": "70A",
        "Model": "Cayenne NAR",
        "Semantics": "Park/Steer Assist"
    },
    {
        "Command": "774",
        "Model": "Cayenne NAR",
        "Semantics": "Park/Steer Assist"
    },
    {
        "Command": "70C",
        "Model": "Cayenne NAR",
        "Semantics": "Steering wheel"
    },
    {
        "Command": "776",
        "Model": "Cayenne NAR",
        "Semantics": "Steering wheel"
    },
    {
        "Command": "714",
        "Model": "Cayenne NAR",
        "Semantics": "Instruments"
    },
    {
        "Command": "77E",
        "Model": "Cayenne NAR",
        "Semantics": "Instruments"
    },
    {
        "Command": "76A",
        "Model": "Cayenne NAR",
        "Semantics": "Aux. Heat"
    },
    {
        "Command": "7D4",
        "Model": "Cayenne NAR",
        "Semantics": "Aux. Heat"
    },
    {
        "Command": "710",
        "Model": "Cayenne NAR",
        "Semantics": "CAN Gateway"
    },
    {
        "Command": "77A",
        "Model": "Cayenne NAR",
        "Semantics": "CAN Gateway"
    },
    {
        "Command": "755",
        "Model": "Cayenne NAR",
        "Semantics": "Level Control"
    },
    {
        "Command": "7BF",
        "Model": "Cayenne NAR",
        "Semantics": "Level Control"
    },
    {
        "Command": "74C",
        "Model": "Cayenne NAR",
        "Semantics": "Seat Mem. Driver"
    },
    {
        "Command": "7B6",
        "Model": "Cayenne NAR",
        "Semantics": "Seat Mem. Driver"
    },
    {
        "Command": "74A",
        "Model": "Cayenne NAR",
        "Semantics": "Door Elect. Driver"
    },
    {
        "Command": "7B4",
        "Model": "Cayenne NAR",
        "Semantics": "Door Elect. Driver"
    },
    {
        "Command": "712",
        "Model": "Cayenne NAR",
        "Semantics": "Steering Assist"
    },
    {
        "Command": "77C",
        "Model": "Cayenne NAR",
        "Semantics": "Steering Assist"
    },
    {
        "Command": "7E6",
        "Model": "Cayenne NAR",
        "Semantics": "Electric Drive"
    },
    {
        "Command": "7EE",
        "Model": "Cayenne NAR",
        "Semantics": "Electric Drive"
    },
    {
        "Command": "74B",
        "Model": "Cayenne NAR",
        "Semantics": "Door Elect. Passenger"
    },
    {
        "Command": "7B5",
        "Model": "Cayenne NAR",
        "Semantics": "Door Elect. Passenger"
    },
    {
        "Command": "752",
        "Model": "Cayenne NAR",
        "Semantics": "Parking Brake"
    },
    {
        "Command": "7BC",
        "Model": "Cayenne NAR",
        "Semantics": "Parking Brake"
    },
    {
        "Command": "754",
        "Model": "Cayenne NAR",
        "Semantics": "Xenon Range"
    },
    {
        "Command": "7BE",
        "Model": "Cayenne NAR",
        "Semantics": "Xenon Range"
    },
    {
        "Command": "723",
        "Model": "Cayenne NAR",
        "Semantics": "Electrical Trunk"
    },
    {
        "Command": "78D",
        "Model": "Cayenne NAR",
        "Semantics": "Electrical Trunk"
    }
]
